ldqn97_mysql_mcp/__init__.py
ldqn97_mysql_mcp/server.py
ldqn97_mysql_mcp_server-0.1.2.dist-info/METADATA
ldqn97_mysql_mcp_server-0.1.2.dist-info/WHEEL
ldqn97_mysql_mcp_server-0.1.2.dist-info/entry_points.txt
ldqn97_mysql_mcp_server-0.1.2.dist-info/top_level.txt
ldqn97_mysql_mcp_server-0.1.2.dist-info/RECORD
